redivis/__init__.py
redivis/_version.py
redivis/classes/Base.py
redivis/classes/Dataset.py
redivis/classes/Datasource.py
redivis/classes/Export.py
redivis/classes/File.py
redivis/classes/Member.py
redivis/classes/Notebook.py
redivis/classes/Organization.py
redivis/classes/Project.py
redivis/classes/Query.py
redivis/classes/Row.py
redivis/classes/Secret.py
redivis/classes/Table.py
redivis/classes/Transform.py
redivis/classes/Upload.py
redivis/classes/User.py
redivis/classes/Variable.py
redivis/classes/Version.py
redivis/classes/Workflow.py
redivis/classes/__init__.py
redivis/common/__init__.py
redivis/common/api_request.py
redivis/common/auth.py
redivis/common/download_files.py
redivis/common/list_rows.py
redivis/common/retryable_download.py
redivis/common/retryable_upload.py
redivis/common/util.py
redivis-0.18.17.dist-info/LICENSE
redivis-0.18.17.dist-info/METADATA
redivis-0.18.17.dist-info/WHEEL
redivis-0.18.17.dist-info/top_level.txt
redivis-0.18.17.dist-info/RECORD
