Metadata-Version: 2.1
Name: redivis
Version: 0.18.17
Summary: Redivis python client library
Home-page: https://github.com/redivis/redivis-python
Author: Redivis Inc.
Author-email: support@redivis.com
License: MIT
Classifier: License :: OSI Approved :: MIT License
Classifier: Programming Language :: Python
Classifier: Programming Language :: Python :: 3
Classifier: Programming Language :: Python :: 3.6
Classifier: Programming Language :: Python :: 3.7
Classifier: Programming Language :: Python :: 3.8
Classifier: Programming Language :: Python :: 3.9
Classifier: Programming Language :: Python :: 3.10
Classifier: Programming Language :: Python :: 3.11
Classifier: Programming Language :: Python :: 3.12
Classifier: Programming Language :: Python :: 3.13
Classifier: Programming Language :: Python :: 3.14
Requires-Python: >=3.6.0
License-File: LICENSE
Requires-Dist: requests >=2.0.0
Requires-Dist: tqdm >=4.64.0
Requires-Dist: pyarrow >=13.0.0
Requires-Dist: dask >=2023.9.3
Requires-Dist: pandas >=2.0.0
Requires-Dist: polars >=0.19
Requires-Dist: geopandas >=0.14.0
Requires-Dist: folium >=0.15.0
Requires-Dist: mapclassify >=2.6.0
Requires-Dist: shapely >=2.0.1
